{
  "usingComponents": {
    "van-tab": "/vantui/tab/index",
    "addr": "/components/order/addr/addr",
    "invoice": "/components/order/invoice/invoice",
    "shopTitle": "/components/order/shopTitle/shopTitle",
    "van-popup": "/vantui/popup/index",
    "van-nav-bar": "/vantui/nav-bar/index",
    "orderConfirmCtn": "/components/order/product/orderConfirmCtn/orderConfirmCtn",
    "van-field": "/vantui/field/index"
  },
    "backgroundTextStyle":"light",
    "navigationBarBackgroundColor": "#fe0000",
    "navigationBarTitleText": "确认订单",
    "navigationBarTextStyle":"white"
}